cserve/__init__.py
cserve/_version.py
cserve/cli/__init__.py
cserve/cli/controller.py
cserve/cli/engine.py
cserve/cli/main.py
cserve/cli/plan.py
cserve-0.0.1.dist-info/LICENSE
cserve-0.0.1.dist-info/METADATA
cserve-0.0.1.dist-info/WHEEL
cserve-0.0.1.dist-info/entry_points.txt
cserve-0.0.1.dist-info/top_level.txt
cserve-0.0.1.dist-info/RECORD
